Metadata-Version: 2.1
Name: pyvic2waranalyzer
Version: 1.4.3
Summary: Victoria 2 War Analyzer written in Python!
Home-page: https://github.com/InternetExplorer404/PyVic2WarAnalyzer
Author: Alvaro
Author-email: 
License: Unlicense
Download-URL: https://github.com/InternetExplorer404/PyVic2WarAnalyzer/archive/refs/tags/v1.4.3.tar.gz
Platform: UNKNOWN
Classifier: Development Status :: 3 - Alpha
Classifier: Intended Audience :: Developers
Classifier: Topic :: Other/Nonlisted Topic
Classifier: License :: OSI Approved :: The Unlicense (Unlicense)
Classifier: Programming Language :: Python :: 3
Classifier: Programming Language :: Python :: 3.4
Classifier: Programming Language :: Python :: 3.5
Classifier: Programming Language :: Python :: 3.6
Provides-Extra: docs
